{"cameraMode":{"drawMode":0,"name":"Shaded","section":"Shading Mode"},"sceneLighting":true,"audioPlay":false,"sceneViewState":{"m_AlwaysRefresh":false,"showFog":true,"showSkybox":true,"showFlares":true,"showImageEffects":true,"showParticleSystems":true,"showVisualEffectGraphs":true,"m_FxEnabled":true},"in2DMode":false,"pivot":{"x":2.100602865219116,"y":1.2568953037261963,"z":0.770271360874176},"rotation":{"x":-0.23842185735702516,"y":-0.5115072131156921,"z":0.1501350849866867,"w":-0.8118213415145874},"size":0.1727219969034195,"orthographic":false}